mediawiki_parser/__init__.py
mediawiki_parser/apostrophes.py
mediawiki_parser/constants.py
mediawiki_parser/html.py
mediawiki_parser/preprocessor.py
mediawiki_parser/preprocessorParser.py
mediawiki_parser/raw.py
mediawiki_parser/text.py
mediawiki_parser/wikitextParser.py
mediawiki_parser_fix-0.4.1.dist-info/COPYING
mediawiki_parser_fix-0.4.1.dist-info/METADATA
mediawiki_parser_fix-0.4.1.dist-info/WHEEL
mediawiki_parser_fix-0.4.1.dist-info/top_level.txt
mediawiki_parser_fix-0.4.1.dist-info/RECORD
