Metadata-Version: 2.1
Name: mediawiki-parser-fix
Version: 0.4.1
Summary: A parser for the MediaWiki syntax, based on Pijnu.
Home-page: https://github.com/vhxs/mediawiki-parser
Author: Erik Rose, Peter Potrowl, Vikram Saraph
Author-email: grinch@grinchcentral.com, peter.potrowl@gmail.com, vikram.saraph.22@gmail.com
License: GPL v3
Keywords: MediaWiki,parser,syntax
Classifier: License :: OSI Approved :: GNU General Public License v3 (GPLv3)
Classifier: Development Status :: 4 - Beta
Classifier: Topic :: Software Development
Classifier: Topic :: Text Processing
Classifier: Topic :: Software Development :: Libraries :: Python Modules
Classifier: Intended Audience :: Developers
Classifier: Programming Language :: Python
License-File: COPYING
Requires-Dist: pijnu (>=20160727)
